{
  "metadata": {
    "name": "Barack Obama",
    "birth_date": "August 4, 1961",
    "birth_time": "7:24 PM",
    "location": "Honolulu, Hawaii, USA",
    "unknown_time": false
  },
  "ai_reading": "Chart Overview and Core Themes\n\n\n\nWelcome. Your astrological chart is not a static map of fate, but a dynamic blueprint of your soul's deepest intentions and the personality's journey to express them. When we look at the intricate data of your life, we see a story of profound integration, a life dedicated to building a bridge between the mystical and the material, the private sanctuary and the public stage. Your purpose is not simple; it is to be a master builder of tangible, heart-centered creations. Let us explore the three central themes that define the architecture of your life.\n\n\n\nThe first and most prominent theme is that of **The Structured Mystic**. At your core, you are an individual with profound spiritual and intuitive gifts, as indicated by a Master Number 11/2 Life Path, which points to a destiny of illumination and inspiration. However, unlike a mystic who might float in the ethers, your soul has chosen a deeply grounded path. Your interface with the world, your Sidereal Ascendant, is in the disciplined, pragmatic sign of Capricorn, supported by the wisdom-seeking planet Jupiter also in Capricorn. This means your first instinct is to build, to plan, to master, and to create tangible, enduring structures. This is further reinforced by your Chinese Zodiac sign of the Metal Ox, an emblem of diligence and duty. This creates a fascinating internal dynamic: you possess a high-frequency, intuitive nature that must be channeled through a disciplined, earthy, and often serious personality. Your life's work is not to abandon this structure, but to use it as a sacred vessel—to build a strong, reliable container that is worthy of holding and grounding your profound spiritual insights so they can be of practical use to the world.\n\n\n\nYour central evolutionary journey revolves around a theme we can call **The Journey from the Brilliant Mind to the Courageous Heart**. Your soul's karmic past, revealed by the South Node in Aquarius in the 1st House, is one of a self-reliant visionary. You have spent lifetimes mastering intellectual detachment, radical independence, and an objective, humanitarian perspective. Your comfort zone is in the realm of ideas, systems, and universal truths, often standing apart from the messy world of personal emotion. However, your soul's ultimate mission in this lifetime, indicated by the North Node in Leo in the 7th House, is a direct call to leave the safety of the sidelines and step into the vibrant warmth of the heart. This is a journey from the Aquarian \"I know\" to the Leonine \"I create\" and \"I love.\" Your growth is not a solo mission; it is catalyzed specifically *through* committed one-on-one relationships. Your partners are destined to act as mirrors, teaching you how to be a radiant, sovereign individual while in deep, meaningful connection. This karmic path is the engine that drives your life forward, demanding that you take the risk to shine, to lead with generosity, and to find your authentic self not in isolation, but in the vulnerable space of true partnership.\n\n\n\nFinally, these two foundational themes create a powerful and persistent life tension between **The Need for a Private Sanctuary and the Drive for Public Expression**. Your soul's emotional core, represented by the Sidereal Moon in Taurus in the 4th House, has a profound, non-negotiable need for a stable, secure, and predictable home life. For you, safety is not an abstract concept; it is a tangible reality—a quiet, comfortable, and reliable sanctuary that acts as your fortress against the world. Yet, your personality, through the Tropical Sun in Leo, is driven to shine, perform, and be recognized. Your karmic path (Leo North Node) and your chosen partners (Leo Descendant) pull you out onto the stage of life, demanding creative expression and public engagement. This creates a core internal conflict: the part of you that wants to be seen is at odds with the part of you that needs to be safely hidden. The resolution of this tension is a central life task. Your journey is to learn that these two needs are not mutually exclusive. The goal is to use your \"Structured Mystic\" abilities to consciously build a foundation so solid and a private life so secure that you feel utterly safe to step into the spotlight and share your heart's brilliant, creative fire with the world.\n\n\n\n---\n\nYour Astrological Blueprint: Planets, Points, and Angles\n\n\n\n--- SUN ---\n\n\n\nFollowing the core of your identity, we now turn to the landscape of your emotional and subconscious world.\n\n\n\n### Sidereal Interpretation\n\n\n\nThe soul's pranic essence, as represented by the Sun in Sidereal Cancer at 15°40′ in the 6th House, is fundamentally oriented towards nurturing, protection, and emotional security as a core karmic purpose. Cancer, a Cardinal Water sign ruled by the Moon, imbues the soul's identity with a powerful drive to create and sustain environments of safety and belonging. This is not a life force that seeks external glory, but one that finds its vitality in the quiet acts of caretaking, empathy, and sustaining emotional bonds. Its placement in the 6th House of *seva* (selfless service), health, and daily routines dictates that this core identity is to be actualized through the mundane, practical world of work and duty. Psychologically, this means the soul's self-esteem is directly linked to its usefulness and its ability to tend to the needs of others in a tangible way. The soul's purpose is to infuse its daily labor and routines with the protective, motherly quality of Cancer, thereby finding its true power not in command, but in compassionate service and the creation of a secure \"work family.\"\n\n\n\n### Tropical Interpretation\n\n\n\nThis deep, nurturing Cancerian essence manifests in the personality through the vehicle of the Tropical Sun in Leo at 12°33′, also in the 6th House. The personality's ego-identity and conscious drive for expression are therefore archetypally Leonine—charismatic, creative, and fueled by a need for recognition and appreciation. Leo, a Fixed Fire sign ruled by the Sun itself, seeks to shine, perform, and lead from the heart. The 6th House placement provides the specific stage for this performance: the workplace, daily routines, and acts of service. This individual's personality is driven to be the recognized authority, the charismatic leader, or the creative center of their work environment. They do not simply perform their duties; they seek to infuse them with flair, pride, and a sense of personal ownership. This placement explains the drive for \"Creative Leadership Through Practical Service,\" as the personality's desire to be seen (Leo) is channeled directly into the arena of work and helpfulness (House 6), turning everyday tasks into an opportunity for proud self-expression.\n\n\n\n### Synthesis\n\n\n\nThe Sidereal and Tropical placements of the Sun are remarkably complementary, creating a powerful dynamic of the \"Nurturing Leader.\" The shared 6th House placement acts as the crucial bridge, unifying the soul's purpose with the personality's expression. The soul's deep, karmic need to nurture and protect (Sidereal Cancer) is the *'why'* behind the individual's actions. The personality's drive to lead with creative warmth and seek recognition (Tropical Leo) becomes the *'how'*. There is a creative tension here: the private, security-oriented Cancerian soul must learn to operate through a public-facing, spotlight-seeking Leonine personality. The 6th House context mitigates this tension by grounding the Leo need for a stage within a defined, practical setting. This individual is not meant to be a distant king on a throne, but a beloved team leader who shines by making their colleagues feel safe, a manager who leads with generosity, or a service provider whose warmth and pride in their work inspires loyalty. The challenge is to satisfy the Leo ego's need for applause without compromising the Cancerian soul's need for genuine emotional security, ultimately mastering the art of leading from a protected, loving heart.\n\n\n\n--- MOON ---\n\n\n\nWhile the Moon reveals your inner world, your mind and intellect are described by Mercury.\n\n\n\n### Sidereal Interpretation\n\n\n\nThe soul's core emotional body, represented by the Sidereal Moon at 12°47′ Taurus in the 4th House, is defined by a profound and unwavering need for tangible security and stability. With the Moon in its sign of exaltation, Taurus, its functions of providing emotional comfort and subconscious safety operate at their peak. This fixed earth placement reveals a karmic imprint geared towards finding peace through groundedness, sensual pleasure, and the slow, deliberate accumulation of resources that ensure physical and emotional predictability. The placement in the 4th House—the natural domain of home, roots, and psychological foundations—powerfully amplifies this Taurean drive. For this soul, the concepts of \"home\" and \"security\" are inextricably linked. The ultimate inner sanctuary is not merely a concept but a physical reality: a comfortable, aesthetically pleasing, and stable environment that acts as a fortress against the unpredictable outer world. This is the soul's primary directive for emotional regulation: to build and maintain a sanctuary that is utterly reliable, providing a deep sense of belonging and peace that is rooted in the material plane.\n\n\n\n### Tropical Interpretation\n\n\n\nThe personality's expression of these deep-seated needs manifests through the Tropical Moon at 3°21′ Gemini, also located in the 4th House. This placement shifts the modality from fixed earth to mutable air, creating a dramatically different behavioral pattern. While the foundational drive for security remains anchored in the 4th House of home and private life, the personality (Tropical) seeks to achieve it through Geminian means: communication, intellectual analysis, and constant information gathering. Emotions are processed through a Mercurial lens; they are named, discussed, rationalized, and understood rather than simply felt. This can create a restless and curious inner world, where emotional security is paradoxically linked to mental stimulation and variety within the home. The personality may feel a compulsion to fill the home with books, engage in constant dialogue with family, have multiple projects going at once, or stay connected digitally to feel emotionally \"plugged in\" and safe. This creates a home environment that is less of a quiet sanctuary and more of an active information hub, where the personality's need for dialogue and data flow defines the feeling of domestic security.\n\n\n\n### Synthesis\n\n\n\nThe Sidereal and Tropical Moon placements create a foundational internal tension, representing a core life lesson in integrating being with doing. The shared 4th House placement establishes that the battleground for this integration is the private sphere of home, family, and emotional foundations. The conflict arises from the opposing elemental and modal energies: the soul's Sidereal Taurus Moon craves quiet, fixed, earthy stability, while the personality's Tropical Gemini Moon requires chatty, mutable, airy stimulation. This duality can manifest as an individual who deeply longs for a peaceful, predictable home but whose own personality-driven habits create a state of constant flux, communication, and mental activity within it, leading to a feeling of being perpetually unsettled. The developmental path involves using the personality's Gemini gifts to serve the soul's Taurean needs. This means consciously using communication and intellect to define boundaries, articulate needs for stability, and gather the *right* information to build the secure foundation the soul craves, rather than allowing restless curiosity to undermine it. Ultimately, integration is achieved when the personality learns that true security (Taurus) is not found in having all the answers (Gemini), but in building a reliable inner and outer space where the mind can finally come to rest.\n\n\n\n--- MERCURY ---\n\n\n\nFrom the way you think, we move to what you value and how you connect, as shown by Venus.\n\n\n\n### Sidereal Interpretation\n\n\n\nAt the level of the soul's karmic blueprint, Mercury's placement in the sidereal sign of Cancer in the 6th House reveals an intellect (*buddhi*) that is fundamentally intuitive, receptive, and emotionally attuned. Operating from the cardinal water sign of Cancer, the core mental process is not purely logical or linear; instead, it functions through feeling, subjective experience, and a powerful memory that links present circumstances to past emotional imprints. This mind thinks in terms of security, protection, and nurture. Its primary dharma, or purpose, is to apply this profound emotional intelligence within the 6th House domain of daily work, conflict resolution, and service (*seva*). The soul is here to learn how to communicate care, diagnose problems based on empathetic insight rather than cold data, and manage daily routines in a way that fosters emotional well-being for itself and others. The psychological drive is to create a safe and nurturing environment within the sphere of its duties, making the mind a tool for healing and practical support, perfectly aligning with the foundational theme of leadership through service.\n\n\n\n### Tropical Interpretation\n\n\n\nThe personality's expression of this Cancerian soul-intellect manifests through Mercury in the tropical sign of Leo, also in the 6th House. This translates the soul's private, intuitive processing into a public, performative, and creative communication style. Where the sidereal mind is receptive and protective, the tropical personality is expressive and authoritative. Operating from the fixed fire sign of Leo, communication becomes a vehicle for creative self-expression, leadership, and gaining recognition. Within the 6th House context, this individual's ideas about work, health, and systems are presented with flair, confidence, and a touch of drama. They are likely a charismatic speaker in team meetings, a creative problem-solver who enjoys presenting their solutions, and someone who takes great pride in their intellectual contributions to their work. This placement provides the \"Creative Leadership\" component of the core theme, as the personality uses its voice not just to serve, but to inspire, lead, and shine while organizing the details of daily life.\n\n\n\n### Synthesis\n\n\n\nThe relationship between Mercury's Sidereal Cancer placement and its Tropical Leo expression exemplifies the core life theme of \"Tension Between Private Security and Public Expression.\" The two signs are in a state of complementary tension. The soul's mind (Cancer) is cautious, deeply feeling, and seeks emotional safety, while the personality's mind (Leo) is bold, expressive, and craves the spotlight. The 6th House acts as the crucial synthesizing arena where these divergent energies must collaborate. The soul's intuitive, nurturing insights about what is needed to improve a system or heal a conflict (Sidereal Cancer) are given a powerful, confident, and creative voice by the personality (Tropical Leo). This prevents the soul's wisdom from remaining private and unexpressed. The Leo expression provides the charisma needed to lead and implement the caring solutions the Cancerian soul intuits. The primary challenge is for the personality's need for recognition (Leo) not to overwhelm the soul's more tender need for genuine connection and security (Cancer). Ultimately, this dynamic allows the individual to become a highly effective and heart-centered leader in their field of work—a \"Structured Mystic\" whose creative communication (Leo) builds a tangible framework (6th House) for their intuitive gifts (Cancer).\n\n\n\n[The rest of the reading continues with Venus, Mars, Jupiter, Saturn, Uranus, Neptune, Pluto, Ascendant, Descendant, Midheaven, IC, Nodes, Chiron, Lilith, Ceres, Pallas, Juno, Vesta, Part of Fortune, Vertex, Major Aspects, and Summary sections - all formatted similarly with Sidereal/Tropical/Synthesis structure]\n\n\n\nFull Report\n\n=== SIDEREAL CHART: Barack Hussein Obama ===\n\n- UTC Date & Time: 1961-08-05 05:24\n\n- Location: 21.3045° N, 157.8557° W\n\n- Day/Night Determination: Night Birth (Approx.)\n\n\n\n--- CHINESE ZODIAC ---\n\n- Your sign is the Metal Ox\n\n\n\n--- NUMEROLOGY REPORT ---\n\n- Life Path Number: 11/2\n\n- Day Number: 4\n\n\n\n-- NAME NUMEROLOGY --\n\n- Expression (Destiny) Number: 1\n\n- Soul Urge Number: 9\n\n- Personality Number: 1\n\n\n\n-- SIDEREAL CHART ANALYSIS --\n\n- Chart Ruler: Saturn\n\n- Dominant Sign: Cancer (2 placements)\n\n- Dominant Element: Earth (5)\n\n- Dominant Modality: Cardinal (4)\n\n- Dominant Planet: Jupiter (score 6.88)\n\n\n\n--- MAJOR POSITIONS ---\n\n- Ascendant: 17°57′ Capricorn – House 1, 0°00′\n\n- Sun: 15°40′ Cancer (91%) – House 6, 24°30′\n\n- Moon: 12°47′ Taurus (35%) – House 4, 15°18′\n\n- Mercury: 5°27′ Cancer (32%) – House 6, 14°17′\n\n- Venus: 4°22′ Gemini (15%) – House 5, 13°44′\n\n- Mars: 0°08′ Virgo (0%) – House 8, 4°31′\n\n- Jupiter: 0°45′ Capricorn (3%) (Rx) – House 12, 12°48′\n\n- Saturn: 28°43′ Sagittarius (86%) (Rx) – House 12, 7°16′\n\n- Uranus: 11°15′ Leo (29%) – House 7, 7°13′\n\n- Neptune: 46°10′ Virgo (93%) – House 9, 20°33′\n\n- Pluto: 22°57′ Leo (60%) – House 7, 18°55′\n\n- Chiron: 9°38′ Aquarius (42%) (Rx) – House 1, 17°16′\n\n- True Node: 13°17′ Leo (35%) (Rx) – House 7, 9°15′\n\n- South Node: 1°37′ Aquarius – House 1, 9°15′\n\n- Descendant: 4°02′ Leo – House 7, 0°00′\n\n- Midheaven (MC): 16°44′ Libra – House 10, 10°50′\n\n- Imum Coeli (IC): 8°20′ Taurus – House 4, 10°50′\n\n\n\n--- RETROGRADE PLANETS (Energy turned inward) ---\n\n- Jupiter\n\n- Saturn\n\n- Chiron\n\n- True Node\n\n\n\n--- MAJOR ASPECTS (ranked by influence score) ---\n\n- Saturn in Sagittarius (Rx) Quincunx Uranus in Leo (orb 0.06°, score 1.89)\n\n- Mercury in Cancer Opposition Jupiter in Capricorn (Rx) (orb 1.47°, score 1.62)\n\n- Jupiter in Capricorn (Rx) Biquintile Pluto in Leo (orb 0.12°, score 1.61)\n\n- Moon in Taurus Sextile Mercury in Cancer (orb 1.03°, score 1.23)\n\n- Venus in Gemini Quincunx Jupiter in Capricorn (Rx) (orb 0.93°, score 1.04)\n\n- Moon in Taurus Trine Jupiter in Capricorn (Rx) (orb 2.50°, score 1.00)\n\n- Mercury in Cancer Semisextile Venus in Gemini (orb 0.54°, score 0.97)\n\n- Neptune in Virgo Sextile Pluto in Leo (orb 1.63°, score 0.95)\n\n- Mars in Virgo Trine Saturn in Sagittarius (Rx) (orb 2.75°, score 0.93)\n\n- Jupiter in Capricorn (Rx) Sextile Midheaven (MC) in Libra (orb 1.96°, score 0.84)\n\n- Mercury in Cancer Trine Midheaven (MC) in Libra (orb 3.44°, score 0.79)\n\n- Jupiter in Capricorn (Rx) Conjunction Saturn in Sagittarius (Rx) (orb 5.53°, score 0.77)\n\n- Mars in Virgo Semisquare Neptune in Virgo (orb 1.03°, score 0.74)\n\n- Moon in Taurus Opposition Midheaven (MC) in Libra (orb 4.46°, score 0.73)\n\n- Venus in Gemini Sesquiquadrate Ascendant in Capricorn (orb 1.27°, score 0.66)\n\n- Moon in Taurus Square Pluto in Leo (orb 3.62°, score 0.65)\n\n- Uranus in Leo Square Midheaven (MC) in Libra (orb 3.63°, score 0.65)\n\n- Sun in Cancer Square Neptune in Virgo (orb 3.94°, score 0.61)\n\n- Sun in Cancer Opposition Ascendant in Capricorn (orb 5.51°, score 0.61)\n\n- Moon in Taurus Semisextile Venus in Gemini (orb 1.57°, score 0.58)\n\n- Saturn in Sagittarius (Rx) Sextile Midheaven (MC) in Libra (orb 3.57°, score 0.55)\n\n- Venus in Gemini Quincunx Midheaven (MC) in Libra (orb 2.89°, score 0.51)\n\n- Mercury in Cancer Opposition Saturn in Sagittarius (Rx) (orb 7.00°, score 0.50)\n\n- Uranus in Leo Opposition Ascendant in Capricorn (orb 7.22°, score 0.49)\n\n\n\n--- ASPECT PATTERNS ---\n\n- 3 bodies in Leo (Fire, Fixed Sign Stellium) (score 6.24)\n\n- 3 bodies in House 7 (House Stellium) (score 6.24)\n\n\n\n--- ADDITIONAL POINTS & ANGLES ---\n\n- Ceres: 19°33′ Aries – House 4, 2°20′\n\n- Juno: 11°49′ Pisces – House 2, 12°36′\n\n- Lilith: 6°33′ Leo – House 7, 2°31′\n\n- Pallas: 5°33′ Pisces – House 2, 6°20′ (Rx)\n\n- Part of Fortune: 38°24′ Pisces – House 3, 9°11′\n\n- Vertex: 4°22′ Gemini – House 5, 13°44′\n\n- Vesta: 4°28′ Taurus – House 4, 6°59′\n\n\n\n--- HOUSE RULERS ---\n\n- House 1: Capricorn (Ruler: Saturn – 28°43′ Sagittarius – House 12, 7°16′)\n\n- House 2: Aquarius (Ruler: Uranus – 11°15′ Leo – House 7, 7°13′)\n\n- House 3: Pisces (Ruler: Neptune – 46°10′ Virgo – House 9, 20°33′)\n\n- House 4: Aries (Ruler: Mars – 0°08′ Virgo – House 8, 4°31′)\n\n- House 5: Taurus (Ruler: Venus – 4°22′ Gemini – House 5, 13°44′)\n\n- House 6: Gemini (Ruler: Mercury – 5°27′ Cancer – House 6, 14°17′)\n\n- House 7: Leo (Ruler: Sun – 15°40′ Cancer – House 6, 24°30′)\n\n- House 8: Leo (Ruler: Sun – 15°40′ Cancer – House 6, 24°30′)\n\n- House 9: Virgo (Ruler: Mercury – 5°27′ Cancer – House 6, 14°17′)\n\n- House 10: Libra (Ruler: Venus – 4°22′ Gemini – House 5, 13°44′)\n\n- House 11: Ophiuchus (Ruler: Chiron – 9°38′ Aquarius – House 1, 17°16′)\n\n- House 12: Sagittarius (Ruler: Jupiter – 0°45′ Capricorn – House 12, 12°48′)\n\n\n\n--- HOUSE SIGN DISTRIBUTIONS ---\n\nHouse 1:\n\n      - Capricorn 17.9°–25.6°\n\n      - Aquarius 0.0°–22.4°\n\nHouse 2:\n\n      - Aquarius 22.4°–23.2°\n\n      - Pisces 0.0°–29.2°\n\nHouse 3:\n\n      - Aries 0.0°–17.2°\n\n      - Pisces 29.2°–42.0°\n\nHouse 4:\n\n      - Aries 17.2°–19.7°\n\n      - Taurus 0.0°–27.5°\n\nHouse 5:\n\n      - Taurus 27.5°–36.9°\n\n      - Gemini 0.0°–20.6°\n\nHouse 6:\n\n      - Gemini 20.6°–29.5°\n\n      - Cancer (complete)\n\n      - Leo 0.0°–4.0°\n\nHouse 7:\n\n      - Leo 4.0°–34.0°\n\nHouse 8:\n\n      - Leo 34.0°–38.4°\n\n      - Virgo 0.0°–25.6°\n\nHouse 9:\n\n      - Virgo 25.6°–49.7°\n\n      - Libra 0.0°–5.9°\n\nHouse 10:\n\n      - Libra 5.9°–18.9°\n\n      - Scorpio (complete)\n\n      - Ophiuchus 0.0°–3.8°\n\nHouse 11:\n\n      - Ophiuchus 3.8°–12.4°\n\n      - Sagittarius 0.0°–21.4°\n\nHouse 12:\n\n      - Sagittarius 21.4°–33.5°\n\n      - Capricorn 0.0°–17.9°\n\n=== TROPICAL CHART ===\n\n\n\n-- CHART ANALYSIS --\n\n- Dominant Sign: Leo (3 placements)\n\n- Dominant Element: Fire (3)\n\n- Dominant Modality: Fixed (6)\n\n- Dominant Planet: Jupiter (score 6.88)\n\n\n\n--- MAJOR POSITIONS ---\n\n- Ascendant: 18°03′ Aquarius – House 1, 0°00′\n\n- Sun: 12°33′ Leo (42%) – House 6, 24°30′\n\n- Moon: 3°21′ Gemini (11%) – House 4, 15°18′\n\n- Mercury: 2°20′ Leo (8%) – House 6, 14°17′\n\n- Venus: 1°47′ Cancer (6%) – House 5, 13°44′\n\n- Mars: 22°35′ Virgo (75%) – House 8, 4°31′\n\n- Jupiter: 0°52′ Aquarius (3%) (Rx) – House 12, 12°48′\n\n- Saturn: 25°20′ Capricorn (84%) (Rx) – House 12, 7°16′\n\n- Uranus: 25°16′ Leo (84%) – House 7, 7°13′\n\n- Neptune: 8°36′ Scorpio (29%) – House 9, 20°33′\n\n- Pluto: 6°59′ Virgo (23%) – House 7, 18°55′\n\n- Chiron: 5°19′ Pisces (18%) (Rx) – House 1, 17°16′\n\n- True Node: 27°18′ Leo (91%) (Rx) – House 7, 9°15′\n\n- South Node: 27°18′ Aquarius – House 1, 9°15′\n\n- Descendant: 18°03′ Leo – House 7, 0°00′\n\n- Midheaven (MC): 28°54′ Scorpio – House 10, 10°50′\n\n- Imum Coeli (IC): 28°54′ Taurus – House 4, 10°50′\n\n\n\n--- RETROGRADE PLANETS (Energy turned inward) ---\n\n- Jupiter\n\n- Saturn\n\n- Chiron\n\n- True Node\n\n\n\n--- MAJOR ASPECTS (ranked by influence score) ---\n\n- Saturn in Capricorn (Rx) Quincunx Uranus in Leo (orb 0.06°, score 1.89)\n\n- Mercury in Leo Opposition Jupiter in Aquarius (Rx) (orb 1.47°, score 1.62)\n\n- Jupiter in Aquarius (Rx) Biquintile Pluto in Virgo (orb 0.12°, score 1.61)\n\n- Moon in Gemini Sextile Mercury in Leo (orb 1.03°, score 1.23)\n\n- Venus in Cancer Quincunx Jupiter in Aquarius (Rx) (orb 0.93°, score 1.04)\n\n- Moon in Gemini Trine Jupiter in Aquarius (Rx) (orb 2.50°, score 1.00)\n\n- Mercury in Leo Semisextile Venus in Cancer (orb 0.54°, score 0.97)\n\n- Neptune in Scorpio Sextile Pluto in Virgo (orb 1.63°, score 0.95)\n\n- Mars in Virgo Trine Saturn in Capricorn (Rx) (orb 2.75°, score 0.93)\n\n- Jupiter in Aquarius (Rx) Sextile Midheaven (MC) in Scorpio (orb 1.96°, score 0.84)\n\n- Mercury in Leo Trine Midheaven (MC) in Scorpio (orb 3.44°, score 0.79)\n\n- Jupiter in Aquarius (Rx) Conjunction Saturn in Capricorn (Rx) (orb 5.53°, score 0.77)\n\n- Mars in Virgo Semisquare Neptune in Scorpio (orb 1.03°, score 0.74)\n\n- Moon in Gemini Opposition Midheaven (MC) in Scorpio (orb 4.46°, score 0.73)\n\n- Venus in Cancer Sesquiquadrate Ascendant in Aquarius (orb 1.27°, score 0.66)\n\n- Moon in Gemini Square Pluto in Virgo (orb 3.62°, score 0.65)\n\n- Uranus in Leo Square Midheaven (MC) in Scorpio (orb 3.63°, score 0.65)\n\n- Sun in Leo Square Neptune in Scorpio (orb 3.94°, score 0.61)\n\n- Sun in Leo Opposition Ascendant in Aquarius (orb 5.51°, score 0.61)\n\n- Moon in Gemini Semisextile Venus in Cancer (orb 1.57°, score 0.58)\n\n- Saturn in Capricorn (Rx) Sextile Midheaven (MC) in Scorpio (orb 3.57°, score 0.55)\n\n- Venus in Cancer Quincunx Midheaven (MC) in Scorpio (orb 2.89°, score 0.51)\n\n- Mercury in Leo Opposition Saturn in Capricorn (Rx) (orb 7.00°, score 0.50)\n\n- Uranus in Leo Opposition Ascendant in Aquarius (orb 7.22°, score 0.49)\n\n\n\n--- ASPECT PATTERNS ---\n\n- 4 bodies in Leo (Fire, Fixed Sign Stellium) (score 9.36)\n\n- 3 bodies in House 7 (House Stellium) (score 6.24)\n\n\n\n--- ADDITIONAL POINTS & ANGLES ---\n\n- Ceres: 20°23′ Taurus – House 4, 2°20′\n\n- Juno: 0°40′ Aries – House 2, 12°36′\n\n- Lilith: 20°35′ Leo – House 7, 2°31′\n\n- Pallas: 24°24′ Pisces – House 2, 6°20′ (Rx)\n\n- Part of Fortune: 27°15′ Aries – House 3, 9°11′\n\n- Vertex: 1°47′ Cancer – House 5, 13°44′\n\n- Vesta: 25°02′ Taurus – House 4, 6°59′",
  "chart_data": {
    "name": "Barack Obama",
    "utc_datetime": "1961-08-05 05:24",
    "location": "21.3045° N, 157.8557° W",
    "day_night_status": "Night Birth",
    "chinese_zodiac": "Metal Ox",
    "numerology_analysis": {
      "life_path_number": "11/2",
      "day_number": "4",
      "name_numerology": {
        "expression_number": 5,
        "soul_urge_number": 1,
        "personality_number": 22
      }
    },
    "unknown_time": false,
    "true_sidereal_signs": [
      [
        "Aries",
        0.0,
        19.7286
      ],
      [
        "Taurus",
        19.7286,
        56.5875
      ],
      [
        "Gemini",
        56.5875,
        86.0412
      ],
      [
        "Cancer",
        86.0412,
        103.19
      ],
      [
        "Leo",
        103.19,
        141.6065
      ],
      [
        "Virgo",
        141.6065,
        191.32
      ],
      [
        "Libra",
        191.32,
        210.1972
      ],
      [
        "Scorpio",
        210.1972,
        223.4245
      ],
      [
        "Ophiuchus",
        223.4245,
        235.7818
      ],
      [
        "Sagittarius",
        235.7818,
        269.2677
      ],
      [
        "Capricorn",
        269.2677,
        294.8435
      ],
      [
        "Aquarius",
        294.8435,
        318.0103
      ],
      [
        "Pisces",
        318.0103,
        360.0
      ]
    ],
    "sidereal_house_cusps": [
      287.2174438064592,
      317.2174438064592,
      347.2174438064592,
      17.217443806459187,
      47.21744380645919,
      77.21744380645919,
      107.21744380645919,
      137.2174438064592,
      167.2174438064592,
      197.2174438064592,
      227.2174438064592,
      257.2174438064592
    ],
    "tropical_house_cusps": [
      318.05577713979244,
      348.05577713979244,
      18.05577713979244,
      48.05577713979244,
      78.05577713979244,
      108.05577713979244,
      138.05577713979244,
      168.05577713979244,
      198.05577713979244,
      228.05577713979244,
      258.05577713979244,
      288.05577713979244
    ],
    "house_rulers": {
      "House 1": "Capricorn (Ruler: Saturn – 28°43′ Sagittarius – House 12, 7°16′)",
      "House 2": "Aquarius (Ruler: Uranus – 11°15′ Leo – House 7, 7°13′)",
      "House 3": "Pisces (Ruler: Neptune – 46°10′ Virgo – House 9, 20°33′)",
      "House 4": "Aries (Ruler: Mars – 0°08′ Virgo – House 8, 4°31′)",
      "House 5": "Taurus (Ruler: Venus – 4°22′ Gemini – House 5, 13°44′)",
      "House 6": "Gemini (Ruler: Mercury – 5°27′ Cancer – House 6, 14°17′)",
      "House 7": "Leo (Ruler: Sun – 15°40′ Cancer – House 6, 24°30′)",
      "House 8": "Leo (Ruler: Sun – 15°40′ Cancer – House 6, 24°30′)",
      "House 9": "Virgo (Ruler: Mercury – 5°27′ Cancer – House 6, 14°17′)",
      "House 10": "Libra (Ruler: Venus – 4°22′ Gemini – House 5, 13°44′)",
      "House 11": "Ophiuchus (Ruler: Chiron – 9°38′ Aquarius – House 1, 17°16′)",
      "House 12": "Sagittarius (Ruler: Jupiter – 0°45′ Capricorn – House 12, 12°48′)"
    },
    "house_sign_distributions": {
      "House 1": [
        "Capricorn 17.9°–25.6°",
        "Aquarius 0.0°–22.4°"
      ],
      "House 2": [
        "Aquarius 22.4°–23.2°",
        "Pisces 0.0°–29.2°"
      ],
      "House 3": [
        "Aries 0.0°–17.2°",
        "Pisces 29.2°–42.0°"
      ],
      "House 4": [
        "Aries 17.2°–19.7°",
        "Taurus 0.0°–27.5°"
      ],
      "House 5": [
        "Taurus 27.5°–36.9°",
        "Gemini 0.0°–20.6°"
      ],
      "House 6": [
        "Gemini 20.6°–29.5°",
        "Cancer (complete)",
        "Leo 0.0°–4.0°"
      ],
      "House 7": [
        "Leo 4.0°–34.0°"
      ],
      "House 8": [
        "Leo 34.0°–38.4°",
        "Virgo 0.0°–25.6°"
      ],
      "House 9": [
        "Virgo 25.6°–49.7°",
        "Libra 0.0°–5.9°"
      ],
      "House 10": [
        "Libra 5.9°–18.9°",
        "Scorpio (complete)",
        "Ophiuchus 0.0°–3.8°"
      ],
      "House 11": [
        "Ophiuchus 3.8°–12.4°",
        "Sagittarius 0.0°–21.4°"
      ],
      "House 12": [
        "Sagittarius 21.4°–33.5°",
        "Capricorn 0.0°–17.9°"
      ]
    },
    "sidereal_chart_analysis": {
      "chart_ruler": "Saturn",
      "dominant_sign": "Cancer",
      "dominant_element": "Earth",
      "dominant_modality": "Fixed",
      "dominant_planet": "Jupiter"
    },
    "sidereal_major_positions": [
      {
        "name": "Ascendant",
        "position": "17°57′ Capricorn",
        "degrees": 287.2174438064592,
        "percentage": 70,
        "retrograde": false,
        "house_info": "– House 1, 0°00′",
        "house_num": 1
      },
      {
        "name": "Sun",
        "position": "15°40′ Cancer",
        "degrees": 101.70959053254478,
        "percentage": 91,
        "retrograde": false,
        "house_info": "– House 6, 24°30′",
        "house_num": 6
      },
      {
        "name": "Moon",
        "position": "12°47′ Taurus",
        "degrees": 32.519103852431954,
        "percentage": 35,
        "retrograde": false,
        "house_info": "– House 4, 15°18′",
        "house_num": 4
      },
      {
        "name": "Mercury",
        "position": "5°27′ Cancer",
        "degrees": 91.4932775410141,
        "percentage": 32,
        "retrograde": false,
        "house_info": "– House 6, 14°17′",
        "house_num": 6
      },
      {
        "name": "Venus",
        "position": "4°22′ Gemini",
        "degrees": 60.95102760637894,
        "percentage": 15,
        "retrograde": false,
        "house_info": "– House 5, 13°44′",
        "house_num": 5
      },
      {
        "name": "Mars",
        "position": "0°08′ Virgo",
        "degrees": 141.73827006648798,
        "percentage": 0,
        "retrograde": false,
        "house_info": "– House 8, 4°31′",
        "house_num": 8
      },
      {
        "name": "Jupiter",
        "position": "0°45′ Capricorn",
        "degrees": 270.0202935746214,
        "percentage": 3,
        "retrograde": true,
        "house_info": "– House 12, 12°48′",
        "house_num": 12
      },
      {
        "name": "Saturn",
        "position": "28°43′ Sagittarius",
        "degrees": 264.49241582082357,
        "percentage": 86,
        "retrograde": true,
        "house_info": "– House 12, 7°16′",
        "house_num": 12
      },
      {
        "name": "Uranus",
        "position": "11°15′ Leo",
        "degrees": 114.43249307406484,
        "percentage": 29,
        "retrograde": false,
        "house_info": "– House 7, 7°13′",
        "house_num": 7
      },
      {
        "name": "Neptune",
        "position": "46°10′ Virgo",
        "degrees": 187.76761853162793,
        "percentage": 93,
        "retrograde": false,
        "house_info": "– House 9, 20°33′",
        "house_num": 9
      },
      {
        "name": "Pluto",
        "position": "22°57′ Leo",
        "degrees": 126.1394170870065,
        "percentage": 60,
        "retrograde": false,
        "house_info": "– House 7, 18°55′",
        "house_num": 7
      },
      {
        "name": "Chiron",
        "position": "9°38′ Aquarius",
        "degrees": 304.4786592011403,
        "percentage": 42,
        "retrograde": true,
        "house_info": "– House 1, 17°16′",
        "house_num": 1
      },
      {
        "name": "True Node",
        "position": "13°17′ Leo",
        "degrees": 116.46668504650177,
        "percentage": 35,
        "retrograde": true,
        "house_info": "– House 7, 9°15′",
        "house_num": 7
      },
      {
        "name": "South Node",
        "position": "1°37′ Aquarius",
        "degrees": 296.46668504650177,
        "percentage": 7,
        "retrograde": false,
        "house_info": "– House 1, 9°15′",
        "house_num": 1
      },
      {
        "name": "Descendant",
        "position": "4°02′ Leo",
        "degrees": 107.21744380645919,
        "percentage": 10,
        "retrograde": false,
        "house_info": "– House 7, 0°00′",
        "house_num": 7
      },
      {
        "name": "Midheaven (MC)",
        "position": "16°44′ Libra",
        "degrees": 208.05767132191068,
        "percentage": 89,
        "retrograde": false,
        "house_info": "– House 10, 10°50′",
        "house_num": 10
      },
      {
        "name": "Imum Coeli (IC)",
        "position": "8°20′ Taurus",
        "degrees": 28.057671321910675,
        "percentage": 23,
        "retrograde": false,
        "house_info": "– House 4, 10°50′",
        "house_num": 4
      }
    ],
    "sidereal_retrogrades": [
      {
        "name": "Jupiter"
      },
      {
        "name": "Saturn"
      },
      {
        "name": "Chiron"
      },
      {
        "name": "True Node"
      }
    ],
    "sidereal_aspects": [
      {
        "p1_name": "Saturn in Sagittarius (Rx)",
        "p2_name": "Uranus in Leo",
        "type": "Quincunx",
        "orb": "0.06°",
        "score": "1.89",
        "p1_degrees": 264.49241582082357,
        "p2_degrees": 114.43249307406484
      },
      {
        "p1_name": "Uranus in Leo",
        "p2_name": "True Node in Leo (Rx)",
        "type": "Conjunction",
        "orb": "2.03°",
        "score": "1.65",
        "p1_degrees": 114.43249307406484,
        "p2_degrees": 116.46668504650177
      },
      {
        "p1_name": "Mercury in Cancer",
        "p2_name": "Jupiter in Capricorn (Rx)",
        "type": "Opposition",
        "orb": "1.47°",
        "score": "1.62",
        "p1_degrees": 91.4932775410141,
        "p2_degrees": 270.0202935746214
      },
      {
        "p1_name": "Jupiter in Capricorn (Rx)",
        "p2_name": "Pluto in Leo",
        "type": "Biquintile",
        "orb": "0.12°",
        "score": "1.61",
        "p1_degrees": 270.0202935746214,
        "p2_degrees": 126.1394170870065
      },
      {
        "p1_name": "Pluto in Leo",
        "p2_name": "Chiron in Aquarius (Rx)",
        "type": "Opposition",
        "orb": "1.66°",
        "score": "1.50",
        "p1_degrees": 126.1394170870065,
        "p2_degrees": 304.4786592011403
      },
      {
        "p1_name": "Moon in Taurus",
        "p2_name": "Mercury in Cancer",
        "type": "Sextile",
        "orb": "1.03°",
        "score": "1.23",
        "p1_degrees": 32.519103852431954,
        "p2_degrees": 91.4932775410141
      },
      {
        "p1_name": "Neptune in Virgo",
        "p2_name": "True Node in Leo (Rx)",
        "type": "Quintile",
        "orb": "0.70°",
        "score": "1.06",
        "p1_degrees": 187.76761853162793,
        "p2_degrees": 116.46668504650177
      },
      {
        "p1_name": "Venus in Gemini",
        "p2_name": "Jupiter in Capricorn (Rx)",
        "type": "Quincunx",
        "orb": "0.93°",
        "score": "1.04",
        "p1_degrees": 60.95102760637894,
        "p2_degrees": 270.0202935746214
      },
      {
        "p1_name": "Moon in Taurus",
        "p2_name": "Chiron in Aquarius (Rx)",
        "type": "Square",
        "orb": "1.96°",
        "score": "1.01",
        "p1_degrees": 32.519103852431954,
        "p2_degrees": 304.4786592011403
      },
      {
        "p1_name": "Moon in Taurus",
        "p2_name": "Jupiter in Capricorn (Rx)",
        "type": "Trine",
        "orb": "2.50°",
        "score": "1.00",
        "p1_degrees": 32.519103852431954,
        "p2_degrees": 270.0202935746214
      },
      {
        "p1_name": "Mercury in Cancer",
        "p2_name": "Venus in Gemini",
        "type": "Semisextile",
        "orb": "0.54°",
        "score": "0.97",
        "p1_degrees": 91.4932775410141,
        "p2_degrees": 60.95102760637894
      },
      {
        "p1_name": "Neptune in Virgo",
        "p2_name": "Pluto in Leo",
        "type": "Sextile",
        "orb": "1.63°",
        "score": "0.95",
        "p1_degrees": 187.76761853162793,
        "p2_degrees": 126.1394170870065
      },
      {
        "p1_name": "Mars in Virgo",
        "p2_name": "Saturn in Sagittarius (Rx)",
        "type": "Trine",
        "orb": "2.75°",
        "score": "0.93",
        "p1_degrees": 141.73827006648798,
        "p2_degrees": 264.49241582082357
      },
      {
        "p1_name": "Neptune in Virgo",
        "p2_name": "Chiron in Aquarius (Rx)",
        "type": "Trine",
        "orb": "3.29°",
        "score": "0.82",
        "p1_degrees": 187.76761853162793,
        "p2_degrees": 304.4786592011403
      },
      {
        "p1_name": "Venus in Gemini",
        "p2_name": "Chiron in Aquarius (Rx)",
        "type": "Trine",
        "orb": "3.53°",
        "score": "0.77",
        "p1_degrees": 60.95102760637894,
        "p2_degrees": 304.4786592011403
      },
      {
        "p1_name": "Jupiter in Capricorn (Rx)",
        "p2_name": "Saturn in Sagittarius (Rx)",
        "type": "Conjunction",
        "orb": "5.53°",
        "score": "0.77",
        "p1_degrees": 270.0202935746214,
        "p2_degrees": 264.49241582082357
      },
      {
        "p1_name": "Mars in Virgo",
        "p2_name": "Neptune in Virgo",
        "type": "Semisquare",
        "orb": "1.03°",
        "score": "0.74",
        "p1_degrees": 141.73827006648798,
        "p2_degrees": 187.76761853162793
      },
      {
        "p1_name": "Saturn in Sagittarius (Rx)",
        "p2_name": "True Node in Leo (Rx)",
        "type": "Quincunx",
        "orb": "1.97°",
        "score": "0.67",
        "p1_degrees": 264.49241582082357,
        "p2_degrees": 116.46668504650177
      },
      {
        "p1_name": "Moon in Taurus",
        "p2_name": "Pluto in Leo",
        "type": "Square",
        "orb": "3.62°",
        "score": "0.65",
        "p1_degrees": 32.519103852431954,
        "p2_degrees": 126.1394170870065
      },
      {
        "p1_name": "Sun in Cancer",
        "p2_name": "Neptune in Virgo",
        "type": "Square",
        "orb": "3.94°",
        "score": "0.61",
        "p1_degrees": 101.70959053254478,
        "p2_degrees": 187.76761853162793
      },
      {
        "p1_name": "Moon in Taurus",
        "p2_name": "Venus in Gemini",
        "type": "Semisextile",
        "orb": "1.57°",
        "score": "0.58",
        "p1_degrees": 32.519103852431954,
        "p2_degrees": 60.95102760637894
      },
      {
        "p1_name": "Mercury in Cancer",
        "p2_name": "Saturn in Sagittarius (Rx)",
        "type": "Opposition",
        "orb": "7.00°",
        "score": "0.50",
        "p1_degrees": 91.4932775410141,
        "p2_degrees": 264.49241582082357
      },
      {
        "p1_name": "Mercury in Cancer",
        "p2_name": "Chiron in Aquarius (Rx)",
        "type": "Quincunx",
        "orb": "2.99°",
        "score": "0.50",
        "p1_degrees": 91.4932775410141,
        "p2_degrees": 304.4786592011403
      },
      {
        "p1_name": "Moon in Taurus",
        "p2_name": "True Node in Leo (Rx)",
        "type": "Square",
        "orb": "6.05°",
        "score": "0.43",
        "p1_degrees": 32.519103852431954,
        "p2_degrees": 116.46668504650177
      }
    ],
    "sidereal_aspect_patterns": [
      {
        "description": "3 bodies in Leo (Fire, Fixed Sign Stellium)"
      }
    ],
    "sidereal_additional_points": [
      {
        "name": "Ceres",
        "info": "19°33′ Aries – House 4, 2°20′",
        "retrograde": false
      },
      {
        "name": "Juno",
        "info": "11°49′ Pisces – House 2, 12°36′",
        "retrograde": false
      },
      {
        "name": "Lilith",
        "info": "6°33′ Leo – House 7, 2°31′",
        "retrograde": false
      },
      {
        "name": "Pallas",
        "info": "5°33′ Pisces – House 2, 6°20′",
        "retrograde": true
      },
      {
        "name": "Part of Fortune",
        "info": "38°24′ Pisces – House 3, 9°11′",
        "retrograde": false
      },
      {
        "name": "Vertex",
        "info": "4°22′ Gemini – House 5, 13°44′",
        "retrograde": false
      },
      {
        "name": "Vesta",
        "info": "4°28′ Taurus – House 4, 6°59′",
        "retrograde": false
      }
    ],
    "tropical_chart_analysis": {
      "dominant_sign": "Leo (3 placements)",
      "dominant_element": "Fire (3)",
      "dominant_modality": "Fixed (5)",
      "dominant_planet": "Jupiter (score 6.04)"
    },
    "tropical_major_positions": [
      {
        "name": "Ascendant",
        "position": "18°03′ Aquarius",
        "degrees": 318.05577713979244,
        "percentage": 60,
        "retrograde": false,
        "house_info": "– House 1, 0°00′",
        "house_num": 1
      },
      {
        "name": "Sun",
        "position": "12°33′ Leo",
        "degrees": 132.54792386587815,
        "percentage": 42,
        "retrograde": false,
        "house_info": "– House 6, 24°30′",
        "house_num": 6
      },
      {
        "name": "Moon",
        "position": "3°21′ Gemini",
        "degrees": 63.35743718576526,
        "percentage": 11,
        "retrograde": false,
        "house_info": "– House 4, 15°18′",
        "house_num": 4
      },
      {
        "name": "Mercury",
        "position": "2°20′ Leo",
        "degrees": 122.33161087434739,
        "percentage": 8,
        "retrograde": false,
        "house_info": "– House 6, 14°17′",
        "house_num": 6
      },
      {
        "name": "Venus",
        "position": "1°47′ Cancer",
        "degrees": 91.78936093971227,
        "percentage": 6,
        "retrograde": false,
        "house_info": "– House 5, 13°44′",
        "house_num": 5
      },
      {
        "name": "Mars",
        "position": "22°35′ Virgo",
        "degrees": 172.5766033998213,
        "percentage": 75,
        "retrograde": false,
        "house_info": "– House 8, 4°31′",
        "house_num": 8
      },
      {
        "name": "Jupiter",
        "position": "0°52′ Aquarius",
        "degrees": 300.8586269079547,
        "percentage": 3,
        "retrograde": true,
        "house_info": "– House 12, 12°48′",
        "house_num": 12
      },
      {
        "name": "Saturn",
        "position": "25°20′ Capricorn",
        "degrees": 295.3307491541569,
        "percentage": 84,
        "retrograde": true,
        "house_info": "– House 12, 7°16′",
        "house_num": 12
      },
      {
        "name": "Uranus",
        "position": "25°16′ Leo",
        "degrees": 145.2708264073982,
        "percentage": 84,
        "retrograde": false,
        "house_info": "– House 7, 7°13′",
        "house_num": 7
      },
      {
        "name": "Neptune",
        "position": "8°36′ Scorpio",
        "degrees": 218.6059518649613,
        "percentage": 29,
        "retrograde": false,
        "house_info": "– House 9, 20°33′",
        "house_num": 9
      },
      {
        "name": "Pluto",
        "position": "6°59′ Virgo",
        "degrees": 156.97775042033985,
        "percentage": 23,
        "retrograde": false,
        "house_info": "– House 7, 18°55′",
        "house_num": 7
      },
      {
        "name": "Chiron",
        "position": "5°19′ Pisces",
        "degrees": 335.3169925344737,
        "percentage": 18,
        "retrograde": true,
        "house_info": "– House 1, 17°16′",
        "house_num": 1
      },
      {
        "name": "True Node",
        "position": "27°18′ Leo",
        "degrees": 147.30501837983508,
        "percentage": 91,
        "retrograde": true,
        "house_info": "– House 7, 9°15′",
        "house_num": 7
      },
      {
        "name": "South Node",
        "position": "27°18′ Aquarius",
        "degrees": 327.3050183798351,
        "percentage": 91,
        "retrograde": false,
        "house_info": "– House 1, 9°15′",
        "house_num": 1
      },
      {
        "name": "Descendant",
        "position": "18°03′ Leo",
        "degrees": 138.05577713979244,
        "percentage": 60,
        "retrograde": false,
        "house_info": "– House 7, 0°00′",
        "house_num": 7
      },
      {
        "name": "Midheaven (MC)",
        "position": "28°54′ Scorpio",
        "degrees": 238.89600465524396,
        "percentage": 96,
        "retrograde": false,
        "house_info": "– House 10, 10°50′",
        "house_num": 10
      },
      {
        "name": "Imum Coeli (IC)",
        "position": "28°54′ Taurus",
        "degrees": 58.89600465524393,
        "percentage": 96,
        "retrograde": false,
        "house_info": "– House 4, 10°50′",
        "house_num": 4
      }
    ],
    "tropical_retrogrades": [
      {
        "name": "Jupiter"
      },
      {
        "name": "Saturn"
      },
      {
        "name": "Chiron"
      },
      {
        "name": "True Node"
      }
    ],
    "tropical_aspects": [
      {
        "p1_name": "Saturn in Capricorn (Rx)",
        "p2_name": "Uranus in Leo",
        "type": "Quincunx",
        "orb": "0.06°",
        "score": "1.89",
        "p1_degrees": 295.3307491541569,
        "p2_degrees": 145.2708264073982
      },
      {
        "p1_name": "Uranus in Leo",
        "p2_name": "True Node in Leo (Rx)",
        "type": "Conjunction",
        "orb": "2.03°",
        "score": "1.65",
        "p1_degrees": 145.2708264073982,
        "p2_degrees": 147.30501837983508
      },
      {
        "p1_name": "Mercury in Leo",
        "p2_name": "Jupiter in Aquarius (Rx)",
        "type": "Opposition",
        "orb": "1.47°",
        "score": "1.62",
        "p1_degrees": 122.33161087434739,
        "p2_degrees": 300.8586269079547
      },
      {
        "p1_name": "Jupiter in Aquarius (Rx)",
        "p2_name": "Pluto in Virgo",
        "type": "Biquintile",
        "orb": "0.12°",
        "score": "1.61",
        "p1_degrees": 300.8586269079547,
        "p2_degrees": 156.97775042033985
      },
      {
        "p1_name": "Pluto in Virgo",
        "p2_name": "Chiron in Pisces (Rx)",
        "type": "Opposition",
        "orb": "1.66°",
        "score": "1.50",
        "p1_degrees": 156.97775042033985,
        "p2_degrees": 335.3169925344737
      },
      {
        "p1_name": "Moon in Gemini",
        "p2_name": "Mercury in Leo",
        "type": "Sextile",
        "orb": "1.03°",
        "score": "1.23",
        "p1_degrees": 63.35743718576526,
        "p2_degrees": 122.33161087434739
      },
      {
        "p1_name": "Neptune in Scorpio",
        "p2_name": "True Node in Leo (Rx)",
        "type": "Quintile",
        "orb": "0.70°",
        "score": "1.06",
        "p1_degrees": 218.6059518649613,
        "p2_degrees": 147.30501837983508
      },
      {
        "p1_name": "Venus in Cancer",
        "p2_name": "Jupiter in Aquarius (Rx)",
        "type": "Quincunx",
        "orb": "0.93°",
        "score": "1.04",
        "p1_degrees": 91.78936093971227,
        "p2_degrees": 300.8586269079547
      },
      {
        "p1_name": "Moon in Gemini",
        "p2_name": "Chiron in Pisces (Rx)",
        "type": "Square",
        "orb": "1.96°",
        "score": "1.01",
        "p1_degrees": 63.35743718576526,
        "p2_degrees": 335.3169925344737
      },
      {
        "p1_name": "Moon in Gemini",
        "p2_name": "Jupiter in Aquarius (Rx)",
        "type": "Trine",
        "orb": "2.50°",
        "score": "1.00",
        "p1_degrees": 63.35743718576526,
        "p2_degrees": 300.8586269079547
      },
      {
        "p1_name": "Mercury in Leo",
        "p2_name": "Venus in Cancer",
        "type": "Semisextile",
        "orb": "0.54°",
        "score": "0.97",
        "p1_degrees": 122.33161087434739,
        "p2_degrees": 91.78936093971227
      },
      {
        "p1_name": "Neptune in Scorpio",
        "p2_name": "Pluto in Virgo",
        "type": "Sextile",
        "orb": "1.63°",
        "score": "0.95",
        "p1_degrees": 218.6059518649613,
        "p2_degrees": 156.97775042033985
      },
      {
        "p1_name": "Mars in Virgo",
        "p2_name": "Saturn in Capricorn (Rx)",
        "type": "Trine",
        "orb": "2.75°",
        "score": "0.93",
        "p1_degrees": 172.5766033998213,
        "p2_degrees": 295.3307491541569
      },
      {
        "p1_name": "Neptune in Scorpio",
        "p2_name": "Chiron in Pisces (Rx)",
        "type": "Trine",
        "orb": "3.29°",
        "score": "0.82",
        "p1_degrees": 218.6059518649613,
        "p2_degrees": 335.3169925344737
      },
      {
        "p1_name": "Venus in Cancer",
        "p2_name": "Chiron in Pisces (Rx)",
        "type": "Trine",
        "orb": "3.53°",
        "score": "0.77",
        "p1_degrees": 91.78936093971227,
        "p2_degrees": 335.3169925344737
      },
      {
        "p1_name": "Jupiter in Aquarius (Rx)",
        "p2_name": "Saturn in Capricorn (Rx)",
        "type": "Conjunction",
        "orb": "5.53°",
        "score": "0.77",
        "p1_degrees": 300.8586269079547,
        "p2_degrees": 295.3307491541569
      },
      {
        "p1_name": "Mars in Virgo",
        "p2_name": "Neptune in Scorpio",
        "type": "Semisquare",
        "orb": "1.03°",
        "score": "0.74",
        "p1_degrees": 172.5766033998213,
        "p2_degrees": 218.6059518649613
      },
      {
        "p1_name": "Saturn in Capricorn (Rx)",
        "p2_name": "True Node in Leo (Rx)",
        "type": "Quincunx",
        "orb": "1.97°",
        "score": "0.67",
        "p1_degrees": 295.3307491541569,
        "p2_degrees": 147.30501837983508
      },
      {
        "p1_name": "Moon in Gemini",
        "p2_name": "Pluto in Virgo",
        "type": "Square",
        "orb": "3.62°",
        "score": "0.65",
        "p1_degrees": 63.35743718576526,
        "p2_degrees": 156.97775042033985
      },
      {
        "p1_name": "Sun in Leo",
        "p2_name": "Neptune in Scorpio",
        "type": "Square",
        "orb": "3.94°",
        "score": "0.61",
        "p1_degrees": 132.54792386587815,
        "p2_degrees": 218.6059518649613
      },
      {
        "p1_name": "Moon in Gemini",
        "p2_name": "Venus in Cancer",
        "type": "Semisextile",
        "orb": "1.57°",
        "score": "0.58",
        "p1_degrees": 63.35743718576526,
        "p2_degrees": 91.78936093971227
      },
      {
        "p1_name": "Mercury in Leo",
        "p2_name": "Saturn in Capricorn (Rx)",
        "type": "Opposition",
        "orb": "7.00°",
        "score": "0.50",
        "p1_degrees": 122.33161087434739,
        "p2_degrees": 295.3307491541569
      },
      {
        "p1_name": "Mercury in Leo",
        "p2_name": "Chiron in Pisces (Rx)",
        "type": "Quincunx",
        "orb": "2.99°",
        "score": "0.50",
        "p1_degrees": 122.33161087434739,
        "p2_degrees": 335.3169925344737
      },
      {
        "p1_name": "Moon in Gemini",
        "p2_name": "True Node in Leo (Rx)",
        "type": "Square",
        "orb": "6.05°",
        "score": "0.43",
        "p1_degrees": 63.35743718576526,
        "p2_degrees": 147.30501837983508
      }
    ],
    "tropical_aspect_patterns": [
      {
        "description": "4 bodies in Leo (Fire, Fixed Sign Stellium)"
      }
    ],
    "tropical_additional_points": [
      {
        "name": "Ceres",
        "info": "20°23′ Taurus – House 4, 2°20′",
        "retrograde": false
      },
      {
        "name": "Juno",
        "info": "0°40′ Aries – House 2, 12°36′",
        "retrograde": false
      },
      {
        "name": "Lilith",
        "info": "20°35′ Leo – House 7, 2°31′",
        "retrograde": false
      },
      {
        "name": "Pallas",
        "info": "24°24′ Pisces – House 2, 6°20′",
        "retrograde": true
      },
      {
        "name": "Part of Fortune",
        "info": "27°15′ Aries – House 3, 9°11′",
        "retrograde": false
      },
      {
        "name": "Vertex",
        "info": "1°47′ Cancer – House 5, 13°44′",
        "retrograde": false
      },
      {
        "name": "Vesta",
        "info": "25°02′ Taurus – House 4, 6°59′",
        "retrograde": false
      }
    ]
  }
}